Metadata-Version: 2.4
Name: ratatui
Version: 0.4.2
Summary: Python bindings for ratatui_ffi (Ratatui C ABI) via ctypes
Author: holo-q
License: MIT License
Project-URL: Homepage, https://github.com/holo-q/ratatui-py
Project-URL: Repository, https://github.com/holo-q/ratatui-py
Project-URL: Issues, https://github.com/holo-q/ratatui-py/issues
Project-URL: Changelog, https://github.com/holo-q/ratatui-py/blob/main/CHANGELOG.md
Project-URL: Documentation, https://github.com/holo-q/ratatui-py#readme
Keywords: ratatui,tui,terminal-ui,terminal,ffi,ctypes,rust,bindings,widgets
Classifier: Development Status :: 3 - Alpha
Classifier: Environment :: Console
Classifier: Intended Audience :: Developers
Classifier: Operating System :: OS Independent
Classifier: Programming Language :: Python
Classifier: Programming Language :: Python :: 3
Classifier: Programming Language :: Python :: 3 :: Only
Classifier: Programming Language :: Rust
Classifier: Programming Language :: C
Classifier: Topic :: Software Development :: Libraries :: Python Modules
Classifier: Topic :: Terminals
Requires-Python: >=3.8
License-File: LICENSE
Dynamic: license-file
